modulitiz_binaries/Init.py
modulitiz_binaries/binaries/ffmpeg.exe
modulitiz_binaries/binaries/ffprobe.exe
modulitiz_binaries/binaries/logo_icona.ico
modulitiz_binaries/binaries/geckodriver/geckodriver_x32.exe
modulitiz_binaries/binaries/geckodriver/geckodriver_x64.exe
modulitiz_binaries/binaries/upx/win64/upx.exe
modulitiz_binaries-2.6.0.dist-info/licenses/LICENSE
modulitiz_binaries-2.6.0.dist-info/METADATA
modulitiz_binaries-2.6.0.dist-info/WHEEL
modulitiz_binaries-2.6.0.dist-info/top_level.txt
modulitiz_binaries-2.6.0.dist-info/RECORD
