Metadata-Version: 2.4
Name: modulitiz_binaries
Version: 2.6.0
Summary: Raccolta dei miei moduli - file binari
Author-email: tiz <sderfo1234@altervista.org>
Classifier: Programming Language :: Python :: 3
Classifier: Operating System :: OS Independent
Requires-Python: >=3.11
License-File: LICENSE
Requires-Dist: modulitiz-micro>=2
Dynamic: license-file
